fengyun_commons/__init__.py
fengyun_commons/api/__init__.py
fengyun_commons/api/status.py
fengyun_commons-0.0.1.dist-info/licenses/LICENSE
fengyun_commons-0.0.1.dist-info/METADATA
fengyun_commons-0.0.1.dist-info/WHEEL
fengyun_commons-0.0.1.dist-info/top_level.txt
fengyun_commons-0.0.1.dist-info/RECORD
