Metadata-Version: 2.4
Name: fengyun-commons
Version: 0.0.1
Summary: Fengyun Commons 是 Fengyun AI 团队维护的基础工具库
Home-page: https://github.com/windcloudai/fengyun-commons
Author: lhybdv
Author-email: 39660787@qq.com
Classifier: Programming Language :: Python :: 3
Classifier: License :: OSI Approved :: Apache Software License
Requires-Python: >=3.10
License-File: LICENSE
Dynamic: author
Dynamic: author-email
Dynamic: classifier
Dynamic: description
Dynamic: description-content-type
Dynamic: home-page
Dynamic: license-file
Dynamic: requires-python
Dynamic: summary
